vcvf/__init__.py
vcvf/face_detector.py
vcvf/data/datafile
vcvf/data/lbp_face_20180629
vcvf/data/test.jpg
vcvf-2.0.0.1.data/data/vcvf/datafile
vcvf-2.0.0.1.dist-info/DESCRIPTION.rst
vcvf-2.0.0.1.dist-info/METADATA
vcvf-2.0.0.1.dist-info/RECORD
vcvf-2.0.0.1.dist-info/WHEEL
vcvf-2.0.0.1.dist-info/entry_points.txt
vcvf-2.0.0.1.dist-info/metadata.json
vcvf-2.0.0.1.dist-info/top_level.txt
